nmaxmin/__init__.py
nmaxmin/nmaxmin.py
nmaxmin-1.0.1.dist-info/LICENSE
nmaxmin-1.0.1.dist-info/METADATA
nmaxmin-1.0.1.dist-info/WHEEL
nmaxmin-1.0.1.dist-info/top_level.txt
nmaxmin-1.0.1.dist-info/RECORD
